mapc_optimal/__init__.py
mapc_optimal/constants.py
mapc_optimal/main.py
mapc_optimal/pricing.py
mapc_optimal/solver.py
mapc_optimal/utils.py
mapc_optimal-0.2.0.dist-info/licenses/LICENSE
mapc_optimal-0.2.0.dist-info/METADATA
mapc_optimal-0.2.0.dist-info/WHEEL
mapc_optimal-0.2.0.dist-info/top_level.txt
mapc_optimal-0.2.0.dist-info/RECORD
