Metadata-Version: 2.4
Name: mapc_optimal
Version: 0.2.0
Summary: Optimal solution of the MAPC (C-SR) problem for IEEE 802.11 networks
Author-email: Maksymilian Wojnar <maksymilian.wojnar@agh.edu.pl>, Wojciech Ciężobka <wojciech.ciezobka@agh.edu.pl>, Artur Tomaszewski <artur.tomaszewski@pg.edu.pl>, Piotr Chołda <piotr.cholda@agh.edu.pl>, Krzysztof Rusek <krzysztof.rusek@agh.edu.pl>, Katarzyna Kosek-Szott <katarzyna.kosek-szott@agh.edu.pl>, Szymon Szott <szymon.szott@agh.edu.pl>
License: Creative Commons Legal Code
Keywords: 802.11,coordinated spatial reuse,multi-access point coordination,optimization
Requires-Python: >=3.12
License-File: LICENSE
Requires-Dist: numpy~=1.26.4
Requires-Dist: pulp~=3.0.2
Dynamic: license-file
